PyDC/PyDC_cli.py
PyDC/README.creole
PyDC/PyDC/CassetteObjects.py
PyDC/PyDC/__init__.py
PyDC/PyDC/base_cli.py
PyDC/PyDC/basic_tokens.py
PyDC/PyDC/bitstream_handler.py
PyDC/PyDC/configs.py
PyDC/PyDC/tests.py
PyDC/PyDC/utils.py
PyDC/PyDC/wave2bitstream.py
PyDC/test_files/HelloWorld1 origin.wav
PyDC/test_files/HelloWorld1 xroar.wav
PyDC/test_files/HelloWorld1.bas
PyDC/test_files/LineNumber Test 01.wav
PyDC/test_files/LineNumber Test 02.wav
PyDC/test_files/LineNumberTest.bas
basic_editor/__init__.py
basic_editor/editor.py
basic_editor/editor_base.py
basic_editor/highlighting.py
basic_editor/scrolled_text.py
basic_editor/status_bar.py
basic_editor/tkinter_utils.py
basic_editor/token_window.py
dragonpy/__init__.py
dragonpy/__main__.py
dragonpy/constants.py
dragonpy/CoCo/CoCo2b_rom.py
dragonpy/CoCo/__init__.py
dragonpy/CoCo/config.py
dragonpy/CoCo/machine.py
dragonpy/CoCo/mem_info.py
dragonpy/CoCo/periphery_coco.py
dragonpy/Dragon32/Dragon32_rom.py
dragonpy/Dragon32/MC6821_PIA.py
dragonpy/Dragon32/MC6847.py
dragonpy/Dragon32/MC6883_SAM.py
dragonpy/Dragon32/__init__.py
dragonpy/Dragon32/cassette.py
dragonpy/Dragon32/config.py
dragonpy/Dragon32/dragon_charmap.py
dragonpy/Dragon32/dragon_font.py
dragonpy/Dragon32/gui_config.py
dragonpy/Dragon32/keyboard_map.py
dragonpy/Dragon32/machine.py
dragonpy/Dragon32/mem_info.py
dragonpy/Dragon32/periphery_dragon.py
dragonpy/Dragon32/speaker.py
dragonpy/Dragon64/6809dasm_comments.py
dragonpy/Dragon64/Dragon 64 in 32 mode.txt
dragonpy/Dragon64/Dragon64_rom.py
dragonpy/Dragon64/__init__.py
dragonpy/Dragon64/config.py
dragonpy/Dragon64/create_mem_info.py
dragonpy/Dragon64/dasm_asm_d64_rom.sh
dragonpy/Dragon64/machine.py
dragonpy/Dragon64/mem_info.py
dragonpy/Multicomp6809/Multicomp6809_rom.py
dragonpy/Multicomp6809/README.creole
dragonpy/Multicomp6809/__init__.py
dragonpy/Multicomp6809/config.py
dragonpy/Multicomp6809/gui.py
dragonpy/Multicomp6809/machine.py
dragonpy/Multicomp6809/periphery_Multicomp6809.py
DragonPyEmulator-0.9.3.dist-info/AUTHORS
DragonPyEmulator-0.9.3.dist-info/LICENSE
DragonPyEmulator-0.9.3.dist-info/METADATA
DragonPyEmulator-0.9.3.dist-info/WHEEL
DragonPyEmulator-0.9.3.dist-info/entry_points.txt
DragonPyEmulator-0.9.3.dist-info/top_level.txt
DragonPyEmulator-0.9.3.dist-info/RECORD
