Metadata-Version: 2.1
Name: DragonPyEmulator
Version: 0.9.3
Summary: Emulator for 6809 CPU based system like Dragon 32 / CoCo written in Python...
Author-email: Jens Diemer <git@jensdiemer.de>
License: GPL-3.0-or-later
Project-URL: Documentation, https://github.com/jedie/DragonPy
Project-URL: Source, https://github.com/jedie/DragonPy
Keywords: Emulator,6809,Dragon,CoCo,Vectrex,tkinter,pypy
Requires-Python: >=3.11
License-File: LICENSE
License-File: AUTHORS
Requires-Dist: MC6809
Requires-Dist: dragonlib >=0.2.0
Requires-Dist: cli-base-utilities
Requires-Dist: pygments
Requires-Dist: bx-py-utils
Requires-Dist: click
Requires-Dist: rich-click
Requires-Dist: rich
Provides-Extra: dev
Requires-Dist: manageprojects ; extra == 'dev'
Requires-Dist: urllib3 ; extra == 'dev'
Requires-Dist: pip-tools ; extra == 'dev'
Requires-Dist: tox ; extra == 'dev'
Requires-Dist: coverage ; extra == 'dev'
Requires-Dist: autopep8 ; extra == 'dev'
Requires-Dist: pyupgrade ; extra == 'dev'
Requires-Dist: flake8 ; extra == 'dev'
Requires-Dist: flake8-bugbear ; extra == 'dev'
Requires-Dist: pyflakes ; extra == 'dev'
Requires-Dist: codespell ; extra == 'dev'
Requires-Dist: EditorConfig ; extra == 'dev'
Requires-Dist: pip-audit ; extra == 'dev'
Requires-Dist: mypy ; extra == 'dev'
Requires-Dist: twine ; extra == 'dev'
Requires-Dist: typeguard ; extra == 'dev'
Requires-Dist: darker[color,flynt,isort] ; extra == 'dev'
Requires-Dist: backports.tarfile ; extra == 'dev'
